llmsherpa/__init__.py
llmsherpa/readers/__init__.py
llmsherpa/readers/file_reader.py
llmsherpa/readers/layout_reader.py
llmsherpa-0.1.3.dist-info/LICENSE
llmsherpa-0.1.3.dist-info/METADATA
llmsherpa-0.1.3.dist-info/WHEEL
llmsherpa-0.1.3.dist-info/top_level.txt
llmsherpa-0.1.3.dist-info/RECORD
