Metadata-Version: 2.1
Name: llmsherpa
Version: 0.1.3
Summary: Strategic APIs to Accelerate LLM Use Cases
Home-page: https://github.com/nlmatics/llmsherpa
Author: Ambika Sukla
Author-email: ambika.sukla@nlmatics.com
License: MIT
Classifier: Development Status :: 5 - Production/Stable
Classifier: Development Status :: 1 - Planning
Classifier: Intended Audience :: Science/Research
Classifier: Intended Audience :: Developers
Classifier: Intended Audience :: Legal Industry
Classifier: License :: OSI Approved :: MIT License
Classifier: Operating System :: POSIX :: Linux
Classifier: Programming Language :: Python :: 3 :: Only
License-File: LICENSE
Requires-Dist: urllib3
